pystatis/__init__.py
pystatis/cache.py
pystatis/config.py
pystatis/db.py
pystatis/exception.py
pystatis/find.py
pystatis/helloworld.py
pystatis/http_helper.py
pystatis/profile.py
pystatis/results.py
pystatis/table.py
pystatis/types.py
pystatis/data/evas.csv
pystatis/data/genesis_regioDB_cubes.csv
pystatis/data/genesis_statistics.csv
pystatis/data/genesis_tables.csv
pystatis/data/regioDB_statistics.csv
pystatis/data/regioDB_tables.csv
pystatis/data/zensusDB_statistics.csv
pystatis/data/zensusDB_tables.csv
pystatis-0.5.4.dist-info/METADATA
pystatis-0.5.4.dist-info/WHEEL
pystatis-0.5.4.dist-info/licenses/LICENSE.txt
pystatis-0.5.4.dist-info/RECORD
