Metadata-Version: 2.4
Name: pystatis
Version: 0.5.4
Summary: Python wrapper for GENESIS web service interface (API) of the Federal Statistical Office.
Project-URL: Repository, https://github.com/CorrelAid/pystatis
Project-URL: Documentation, https://correlaid.github.io/pystatis/
Author-email: Michael Aydinbas <michael.aydinbas@gmail.com>, Ariz Weber <ariz.weber@protonmail.com>, CorrelAid <info@correlaid.org>, Daniel Pleus <danielpleus@gmail.com>, Felix Schmitz <felix.schmitz@philosophy-economics.de>, Frederik Hering <jobs.fhering@gmail.com>, Marco Hübner <marco_huebner1@gmx.de>, Jonas Berger <jonas.bergner97@gmx.de>
Maintainer-email: Michael Aydinbas <michael.aydinbas@gmail.com>
License-File: LICENSE.txt
Classifier: Development Status :: 3 - Alpha
Classifier: Intended Audience :: Science/Research
Classifier: License :: OSI Approved :: MIT License
Classifier: Operating System :: MacOS
Classifier: Operating System :: Microsoft
Classifier: Operating System :: POSIX
Classifier: Operating System :: Unix
Classifier: Programming Language :: Python :: 3
Classifier: Programming Language :: Python :: 3 :: Only
Classifier: Programming Language :: Python :: 3.11
Classifier: Programming Language :: Python :: 3.12
Classifier: Programming Language :: Python :: 3.13
Classifier: Topic :: Scientific/Engineering
Classifier: Topic :: Scientific/Engineering :: Information Analysis
Classifier: Topic :: Software Development :: Libraries :: Python Modules
Requires-Python: >=3.11
Requires-Dist: pandas~=2.0
Requires-Dist: requests<3,>=2.27.1
Requires-Dist: tabulate<0.10,>=0.9.0
